convertLambda/__init__.py
convertLambda/convertLambda.py
convertLambda-1.0.0.dist-info/LICENSE
convertLambda-1.0.0.dist-info/METADATA
convertLambda-1.0.0.dist-info/WHEEL
convertLambda-1.0.0.dist-info/top_level.txt
convertLambda-1.0.0.dist-info/RECORD
